nexarch/__init__.py
nexarch/auto_discovery.py
nexarch/client.py
nexarch/loggers.py
nexarch/middleware.py
nexarch/models.py
nexarch/py.typed
nexarch/queue.py
nexarch/router.py
nexarch/utils.py
nexarch/exporters/__init__.py
nexarch/exporters/base.py
nexarch/exporters/http.py
nexarch/exporters/local_json.py
nexarch/instrumentation/__init__.py
nexarch/instrumentation/db_patch.py
nexarch/instrumentation/httpx_patch.py
nexarch/instrumentation/requests_patch.py
nexarch/tracing/__init__.py
nexarch/tracing/context.py
nexarch/tracing/sampler.py
nexarch/tracing/span.py
nexarch_sdk-0.2.0.dist-info/licenses/LICENSE
nexarch_sdk-0.2.0.dist-info/METADATA
nexarch_sdk-0.2.0.dist-info/WHEEL
nexarch_sdk-0.2.0.dist-info/top_level.txt
nexarch_sdk-0.2.0.dist-info/RECORD
