Metadata-Version: 2.4
Name: nexarch-sdk
Version: 0.2.0
Summary: Nexarch SDK for runtime architecture intelligence and observability
Author: Nexarch Team
License: MIT
Project-URL: Homepage, https://github.com/nexarch/nexarch-sdk
Project-URL: Documentation, https://docs.nexarch.io
Project-URL: Repository, https://github.com/nexarch/nexarch-sdk
Keywords: architecture,observability,fastapi,monitoring,tracing
Classifier: Development Status :: 3 - Alpha
Classifier: Intended Audience :: Developers
Classifier: License :: OSI Approved :: MIT License
Classifier: Programming Language :: Python :: 3
Classifier: Programming Language :: Python :: 3.8
Classifier: Programming Language :: Python :: 3.9
Classifier: Programming Language :: Python :: 3.10
Classifier: Programming Language :: Python :: 3.11
Classifier: Programming Language :: Python :: 3.12
Classifier: Framework :: FastAPI
Requires-Python: >=3.8
License-File: LICENSE
Requires-Dist: fastapi>=0.100.0
Requires-Dist: starlette>=0.27.0
Provides-Extra: dev
Requires-Dist: pytest>=7.0; extra == "dev"
Requires-Dist: pytest-asyncio>=0.21.0; extra == "dev"
Requires-Dist: black>=23.0; extra == "dev"
Requires-Dist: ruff>=0.1.0; extra == "dev"
Dynamic: license-file
